core/DataProcessing.py
core/Detector.py
core/__init__.py
core/custom_logging/__init__.py
core/custom_logging/custom_logging.py
core/database/__init__.py
core/database/connections.py
core/detector_modules/AreaAndROIExtractor.py
core/detector_modules/AreaMapper.py
core/detector_modules/FCNMapper.py
core/detector_modules/FocusMapper.py
core/detector_modules/ImageLoader.py
core/detector_modules/MapComparator.py
core/detector_modules/NucleusMapper.py
core/detector_modules/QualityTester.py
core/detector_modules/__init__.py
core/roi/AreaAnalysis.py
core/roi/ROI.py
core/roi/ROIHandler.py
core/roi/__init__.py
fcn/FCN.py
fcn/__init__.py
fcn/model/__init__.py
fcn/training_notebook/__init__.py
fcn/training_notebook/parallel_functions.py
gui/NucDetectAppQT.py
gui/Paths.py
gui/Plots.py
gui/Util.py
gui/__init__.py
gui/loader.py
gui/definitions/__init__.py
gui/definitions/icons.py
gui/definitions/css/__init__.py
gui/definitions/images/__init__.py
gui/definitions/ui/__init__.py
gui/dialogs/GraphicsItems.py
gui/dialogs/__init__.py
gui/dialogs/data.py
gui/dialogs/selection.py
gui/dialogs/settings.py
gui/settings/Widgets.py
gui/settings/__init__.py
gui/settings/menu_checkbox.ui
gui/settings/menu_combo.ui
gui/settings/menu_decimal_spin.ui
gui/settings/menu_dial.ui
gui/settings/menu_slider.ui
gui/settings/menu_spin.ui
gui/settings/menu_text.ui
gui/settings/menu_widget.ui
gui/settings/parser.py
gui/settings/settings.ini
gui/settings/settings.json
nucdetect-1.0.dist-info/licenses/licence.txt
nucdetect-1.0.dist-info/METADATA
nucdetect-1.0.dist-info/WHEEL
nucdetect-1.0.dist-info/top_level.txt
nucdetect-1.0.dist-info/RECORD
