Metadata-Version: 2.4
Name: NucDetect
Version: 1.0
Summary: Module to quantify intranuclear foci on basis of immunofluorescence images.
Home-page: https://github.com/SilMon/NucDetect
Author: Romano Weiss
Classifier: Development Status :: 5 - Production/Stable
Classifier: License :: OSI Approved :: GNU General Public License v3 (GPLv3)
Classifier: Intended Audience :: Developers
Classifier: Intended Audience :: Science/Research
Classifier: Programming Language :: Python :: 3.12
License-File: licence.txt
Requires-Dist: tensorflow-cpu>=2.17.0
Requires-Dist: scikit-image>=0.16.2
Requires-Dist: matplotlib>=3.1.3
Requires-Dist: seaborn>=0.13.2
Requires-Dist: statannotations>=0.7.2
Requires-Dist: pyqt5>=5.14.1
Requires-Dist: numba>=0.48.0
Requires-Dist: pillow>=11.13.0
Requires-Dist: qtawesome==1.3.1
Requires-Dist: piexif>=1.1.3
Requires-Dist: pyqtgraph>=0.14.0
Requires-Dist: pandas>=2.1.4
Requires-Dist: imagecodecs>=2026.1.1
Requires-Dist: openpyxl>=3.1.5
Requires-Dist: PyWavelets>=1.9.0
Dynamic: author
Dynamic: classifier
Dynamic: description
Dynamic: description-content-type
Dynamic: home-page
Dynamic: license-file
Dynamic: requires-dist
Dynamic: summary
